warapidpro/__init__.py
warapidpro/apps.py
warapidpro/handlers.py
warapidpro/models.py
warapidpro/tasks.py
warapidpro/types.py
warapidpro/urls.py
warapidpro/utils.py
warapidpro/views.py
warapidpro/templates/channels/types/whatsapp_base.html
warapidpro/templates/channels/types/wad/claim.haml
warapidpro/templates/channels/types/wag/claim.haml
warapidpro-1.2.19.dist-info/DESCRIPTION.rst
warapidpro-1.2.19.dist-info/METADATA
warapidpro-1.2.19.dist-info/RECORD
warapidpro-1.2.19.dist-info/WHEEL
warapidpro-1.2.19.dist-info/metadata.json
warapidpro-1.2.19.dist-info/top_level.txt
