Metadata-Version: 2.0
Name: warapidpro
Version: 1.2.19
Summary: warapidpro
Home-page: https://github.com/praekeltfoundation/wa-rapidpro
Author: Simon de Haan
Author-email: simon@praekelt.org
License: UNKNOWN
Keywords: warapidpro
Platform: UNKNOWN
Classifier: Intended Audience :: Developers
Classifier: Natural Language :: English
Classifier: Programming Language :: Python :: 2.7
Classifier: Programming Language :: Python :: 3.6
